jupyter_nb_double_quote_to_single_quote/__init__.py
jupyter_nb_double_quote_to_single_quote/_helper.py
jupyter_nb_double_quote_to_single_quote/_main.py
jupyter_nb_double_quote_to_single_quote-0.1.4.dist-info/LICENSE
jupyter_nb_double_quote_to_single_quote-0.1.4.dist-info/METADATA
jupyter_nb_double_quote_to_single_quote-0.1.4.dist-info/WHEEL
jupyter_nb_double_quote_to_single_quote-0.1.4.dist-info/entry_points.txt
jupyter_nb_double_quote_to_single_quote-0.1.4.dist-info/top_level.txt
jupyter_nb_double_quote_to_single_quote-0.1.4.dist-info/RECORD
