Metadata-Version: 2.1
Name: jupyter-nb-double-quote-to-single-quote
Version: 0.1.4
Summary: Command line tool and pre-commit hook to convert double quotes to single quotes in Jupyter notebook code cells
Home-page: https://github.com/cyyc1/jupyter-nb-double-quote-to-single-quote
License: MIT
Classifier: License :: OSI Approved :: MIT License
Classifier: Programming Language :: Python :: 3
Classifier: Programming Language :: Python :: 3 :: Only
Requires-Python: >=3.7
License-File: LICENSE
Requires-Dist: jupyter-notebook-parser (>=0.1.4)
